{
  "name": "Servetele de Unica Folosinta pentru Ingrijirea Urechilor Cainilor 50 buc 29392",
  "subCategory": "Igiena Ochi si Urechi ",
  "shortDescription": "Tampoane de deget de unică folosință pentru caini, pisici și alte animale mici, cu loțiune de curățare hrănitoare.",
  "image": "https://cdn.quicq.io/pm-d2ac76g66dj6h3/catalog/product/cache/1/image/750x750/9df78eab33525d08d6e5fb8d27136e95/s/e/servetele-de-unica-folosinta-pentru-ingrijirea-urechilor-cainilor-50-buc-29392-1.jpg",
  "description": "Titlu produs: Servetele de Unica Folosinta pentru Ingrijirea Urechilor Cainilor 50 buc 29392\nTampoane de deget de unică folosință pentru caini, pisici și alte animale mici, cu loțiune de curățare hrănitoare. Aloe vera și hamamelis.",
  "url": "https://www.petmart.ro/servetele-de-unica-folosinta-pentru-ingrijirea-urechilor-cainilor-50-buc-29392.html"
}