{
  "name": "Brit Premium Cat Junior plic cu carne de pui, 100 g",
  "subCategory": "Hrana umeda Pisici",
  "shortDescription": "Brit Premium Junior Plic cu carne de pui este o formula de hrana, premium pentru pisici in crestere.",
  "image": "https://cdn.quicq.io/pm-d2ac76g66dj6h3/catalog/product/cache/1/image/750x750/9df78eab33525d08d6e5fb8d27136e95/b/p/bp_cat_pouch_chicken_for_kitten.jpg",
  "description": "Titlu produs: Brit Premium Cat Junior plic cu carne de pui, 100 g\nBrit Premium Junior Plic cu carne de pui este o formula de hrana, premium pentru pisici in crestere. Producator: Brit Grupa: Pet Food Cat Tip hrana: Hrana de intretinere Varsta: Junior Talie: Toate Pentru: Pisica Aroma: Pui Ambalare: Plic Subcategorie: Hrana",
  "url": "https://www.petmart.ro/brit-premium-cat-junior-plic-cu-carne-de-pui-100-g.html"
}