{
  "name": "Royal Canin Skin & Coat Formula, 85 g",
  "subCategory": "Diete veterinare Pisici",
  "shortDescription": "Royal Canin Skin & Coat Formula",
  "image": "https://cdn.quicq.io/pm-d2ac76g66dj6h3/catalog/product/cache/1/image/750x750/9df78eab33525d08d6e5fb8d27136e95/r/o/royal_canin_skin_coat_formula.jpeg",
  "description": "Titlu produs: Royal Canin Skin & Coat Formula, 85 g\nRoyal Canin Skin & Coat Formula este o hrana umeda completa pentru pisici adulte (cu varsta mai mare de 1 an) ce prezinta sensibilitate la nivelul pielii. Compozitie: carne si derivate din carne peste si derivate din peste cereale derivate de origine vegetala extract de proteine vegetale minerale drojdii zaharuri diferite. Analiza medie: proteine 10% grasimi 4% cenusa 1 5% fibre 1 5% umiditate 79%",
  "url": "https://www.petmart.ro/royal-canin-skin-coat-formula-85-g.html"
}