{
  "name": "Pet Care forfecuta unghii",
  "subCategory": "Forfecute, Clesti",
  "shortDescription": "Forfecuta pentru ajustarea unghiilor la caini",
  "image": "https://cdn.quicq.io/pm-d2ac76g66dj6h3/catalog/product/cache/1/image/750x750/9df78eab33525d08d6e5fb8d27136e95/f/o/forfecuta-unghii.jpg",
  "description": "Informatii produs: - ideal pentru a mentine unghiile cainelui in conditii de sanatate- un produs de calitate pentru igiena completa a animalului dumneavoastra preferat- foarte usor de folosit si sigur pentru a nu taia din partea unghiei vascularizata Animăluțele noastre merită toată dragostea pe care le-o putem oferi. Animale sănătoase îngrijite cu Pet Care forfecuta unghii Necuvântătoarele din viața noastră merită cele mai bune produse de la Zolux. PetMart este un pet shop care îți oferă produse premium din categoria forfecute, clesti marca Zolux pentru a-ți răsfăța prietenul nevorbitor. Calitatea este cel mai important element pe care punem preț. Astfel, produsul Pet Care forfecuta unghii este fabricat și depozitat la standarde ridicate. Este perfect pentru pisici! Iubitorii de animale pot comanda produsul Pet Care forfecuta unghii la orice oră din zi sau din noapte. La petshop-ul din colț nu găsești Pet Care forfecuta unghii? PetMart îți livrează extrem de rapid produsele din categoria forfecute, clesti de care ai nevoie oriunde în România. Este cunoscut faptul că animalele sunt foarte sensibile. La PetMart este foarte important ca produsele să aducă un plus de sănătate pentru pisici. Pe site-ul magazinului online PetMart, prezent încă din 2009 pe piață, regăsiți Pet Care forfecuta unghii la prețul 18,75 RON. Fie că ești din București sau din altă zona a țării, nu ezita să comanzi produsele Zolux pentru pisici de la Pet Mart!",
  "url": "https://www.petmart.ro/pet-care-forfecuta-unghii.html"
}